twitlim/VERSION
twitlim/__init__.py
twitlim/helpers.py
twitlim/twitlim.py
twitlim-0.3.2.dist-info/LICENSE.txt
twitlim-0.3.2.dist-info/METADATA
twitlim-0.3.2.dist-info/WHEEL
twitlim-0.3.2.dist-info/entry_points.txt
twitlim-0.3.2.dist-info/top_level.txt
twitlim-0.3.2.dist-info/RECORD
